kserve/__init__.py
kserve/api_client.py
kserve/configuration.py
kserve/errors.py
kserve/exceptions.py
kserve/metrics.py
kserve/model.py
kserve/model_repository.py
kserve/model_server.py
kserve/rest.py
kserve/storage.py
kserve/api/__init__.py
kserve/api/creds_utils.py
kserve/api/kserve_client.py
kserve/api/watch.py
kserve/constants/__init__.py
kserve/constants/constants.py
kserve/grpc/__init__.py
kserve/grpc/grpc_predict_v2_pb2.py
kserve/grpc/grpc_predict_v2_pb2_grpc.py
kserve/grpc/interceptors.py
kserve/grpc/server.py
kserve/grpc/servicer.py
kserve/handlers/__init__.py
kserve/handlers/dataplane.py
kserve/handlers/model_repository_extension.py
kserve/handlers/v1_endpoints.py
kserve/handlers/v2_datamodels.py
kserve/handlers/v2_endpoints.py
kserve/models/__init__.py
kserve/models/knative_addressable.py
kserve/models/knative_condition.py
kserve/models/knative_status.py
kserve/models/knative_url.py
kserve/models/knative_volatile_time.py
kserve/models/net_url_userinfo.py
kserve/models/v1_time.py
kserve/models/v1alpha1_built_in_adapter.py
kserve/models/v1alpha1_cluster_serving_runtime.py
kserve/models/v1alpha1_cluster_serving_runtime_list.py
kserve/models/v1alpha1_container.py
kserve/models/v1alpha1_inference_graph.py
kserve/models/v1alpha1_inference_graph_list.py
kserve/models/v1alpha1_inference_graph_spec.py
kserve/models/v1alpha1_inference_graph_status.py
kserve/models/v1alpha1_inference_router.py
kserve/models/v1alpha1_inference_step.py
kserve/models/v1alpha1_inference_target.py
kserve/models/v1alpha1_model_spec.py
kserve/models/v1alpha1_serving_runtime.py
kserve/models/v1alpha1_serving_runtime_list.py
kserve/models/v1alpha1_serving_runtime_pod_spec.py
kserve/models/v1alpha1_serving_runtime_spec.py
kserve/models/v1alpha1_storage_helper.py
kserve/models/v1alpha1_supported_model_format.py
kserve/models/v1alpha1_trained_model.py
kserve/models/v1alpha1_trained_model_list.py
kserve/models/v1alpha1_trained_model_spec.py
kserve/models/v1beta1_aix_explainer_spec.py
kserve_mathking-0.10.0rc3.dist-info/METADATA
kserve_mathking-0.10.0rc3.dist-info/WHEEL
kserve_mathking-0.10.0rc3.dist-info/top_level.txt
kserve_mathking-0.10.0rc3.dist-info/RECORD
