Metadata-Version: 2.1
Name: kserve-mathking
Version: 0.10.0rc3
Summary: KServe Python SDK
Home-page: https://github.com/kserve/kserve/tree/master/python/kserve
Author: teamturing
Author-email: admin-developers@teamturing.com
License: Apache License Version 2.0
Classifier: Programming Language :: Python :: 3
Classifier: Programming Language :: Python :: 3.9
Classifier: License :: OSI Approved :: Apache Software License
Classifier: Operating System :: OS Independent
Requires-Python: >=3.9
Requires-Dist: six (>=1.16.0)
Requires-Dist: python-dateutil (>=2.8.0)
Requires-Dist: setuptools (>=59.5.0)
Requires-Dist: urllib3 (>=1.26.8)
Requires-Dist: kubernetes (>=18.20.0)
Requires-Dist: argparse (>=1.4.0)
Requires-Dist: minio (<=7.1.3,>=4.0.9)
Requires-Dist: google-cloud-storage (>=1.20.0)
Requires-Dist: adal (>=1.2.7)
Requires-Dist: table-logger (>=0.3.6)
Requires-Dist: numpy (<1.24.0,>=1.21.5)
Requires-Dist: azure-storage-blob (==12.9.0)
Requires-Dist: azure-storage-file-share (==12.7.0)
Requires-Dist: azure-identity (>=1.8.0)
Requires-Dist: cloudevents (>=1.6.2)
Requires-Dist: avro (>=1.11.0)
Requires-Dist: boto3 (~=1.21)
Requires-Dist: psutil (>=5.9.0)
Requires-Dist: ray[serve] (==2.0.0)
Requires-Dist: grpcio (>=1.34.0)
Requires-Dist: tritonclient (==2.18.0)
Requires-Dist: protobuf (~=3.19.0)
Requires-Dist: prometheus-client (>=0.13.1)
Requires-Dist: orjson (>=3.8.0)
Requires-Dist: httpx (>=0.23.0)
Requires-Dist: fastapi (<=0.88.0,>=0.85.0)
Requires-Dist: uvicorn (>=0.16.0)
Provides-Extra: test
Requires-Dist: pytest ; extra == 'test'
Requires-Dist: pytest-xdist ; extra == 'test'
Requires-Dist: pytest-cov ; extra == 'test'
Requires-Dist: pytest-asyncio ; extra == 'test'
Requires-Dist: pytest-tornasync ; extra == 'test'
Requires-Dist: mypy ; extra == 'test'
Requires-Dist: portforward ; extra == 'test'
